tinygrid/__init__.py
tinygrid/base.py
tinygrid/ercot.py
tinygrid/errors.py
tinygrid/auth/__init__.py
tinygrid/auth/ercot_auth.py
tinygrid/constants/__init__.py
tinygrid/constants/ercot.py
tinygrid/historical/__init__.py
tinygrid/historical/ercot.py
tinygrid/utils/__init__.py
tinygrid/utils/dates.py
tinygrid/utils/decorators.py
tinygrid/utils/tz.py
tinygrid-0.1.0a0.dist-info/METADATA
tinygrid-0.1.0a0.dist-info/WHEEL
tinygrid-0.1.0a0.dist-info/top_level.txt
tinygrid-0.1.0a0.dist-info/RECORD
