Metadata-Version: 2.4
Name: tinygrid
Version: 0.1.0a0
Summary: A unified Python SDK for accessing grid data from all major US Independent System Operators (ISOs)
Author-email: Kevin Kenyon <kevin@poweredbylight.com>
License-Expression: MIT
Project-URL: Homepage, https://github.com/kvkenyon/tinygrid
Project-URL: Repository, https://github.com/kvkenyon/tinygrid
Project-URL: Issues, https://github.com/kvkenyon/tinygrid/issues
Keywords: ercot,iso,electricity,grid,energy,api,sdk
Classifier: Development Status :: 3 - Alpha
Classifier: Intended Audience :: Developers
Classifier: Programming Language :: Python :: 3
Classifier: Programming Language :: Python :: 3.10
Classifier: Programming Language :: Python :: 3.11
Classifier: Programming Language :: Python :: 3.12
Classifier: Programming Language :: Python :: 3.13
Classifier: Topic :: Software Development :: Libraries :: Python Modules
Requires-Python: >=3.10
Requires-Dist: pyercot
Requires-Dist: python-dotenv>=1.0.0
Requires-Dist: tenacity>=8.0.0
Requires-Dist: pandas>=2.0.0
Provides-Extra: dev
Requires-Dist: pytest>=7.4.0; extra == "dev"
Requires-Dist: pytest-asyncio>=0.21.0; extra == "dev"
Requires-Dist: pytest-cov>=4.1.0; extra == "dev"
Requires-Dist: ruff>=0.1.0; extra == "dev"
Requires-Dist: pyright>=1.1.0; extra == "dev"
Requires-Dist: pandas>=2.3.3; extra == "dev"
Requires-Dist: respx>=0.21.0; extra == "dev"
